{
  "sections": {
    "product-hero": {
      "type": "product-hero",
      "settings": {
        "desktop_image": "shopify:\/\/shop_images\/image_1.png",
        "mobile_image": "shopify:\/\/shop_images\/image_8.png"
      }
    },
    "huntary": {
      "type": "huntary",
      "settings": {
        "social_icon1": "shopify:\/\/shop_images\/Social_Icons_4.png",
        "social_text1": "Instagram",
        "socail_url1": "https:\/\/www.instagram.com\/safehouse_tech",
        "social_icon2": "shopify:\/\/shop_images\/Social_Icons_5.png",
        "social_text2": "Facebook",
        "socail_url2": "https:\/\/www.facebook.com\/safehousetech\/",
        "social_icon3": "shopify:\/\/shop_images\/Social_Icons_6.png",
        "social_text3": "LinkedIn",
        "socail_url3": "https:\/\/in.linkedin.com\/company\/safehousetech",
        "social_icon4": "shopify:\/\/shop_images\/Social_Icons_8.png",
        "social_text4": "Whatsapp",
        "socail_url4": "https:\/\/wa.me\/+919625084349"
      }
    },
    "product-membership": {
      "type": "product-membership",
      "settings": {
      }
    },
    "pdp-features": {
      "type": "pdp-features",
      "settings": {
      }
    },
    "proudly-featured": {
      "type": "proudly-featured",
      "settings": {
      }
    },
    "people-say": {
      "type": "people-say",
      "settings": {
      }
    },
    "need-safehouse": {
      "type": "need-safehouse",
      "settings": {
      }
    },
    "money-back": {
      "type": "money-back",
      "settings": {
      }
    },
    "need-help": {
      "type": "need-help",
      "settings": {
        "need_email": "insupport@safehousetech.in",
        "need_whasapp": "9625084349"
      }
    }
  },
  "order": [
    "product-hero",
    "huntary",
    "product-membership",
    "pdp-features",
    "proudly-featured",
    "people-say",
    "need-safehouse",
    "money-back",
    "need-help"
  ]
}
